YoClient-0.0.2.dist-info/DESCRIPTION.rst
YoClient-0.0.2.dist-info/METADATA
YoClient-0.0.2.dist-info/RECORD
YoClient-0.0.2.dist-info/WHEEL
YoClient-0.0.2.dist-info/metadata.json
YoClient-0.0.2.dist-info/top_level.txt
yo_client/__init__.py
yo_client/models.py
yo_client/request_parameters.py
yo_client/urls.py
yo_client/yo_client.py
