Metadata-Version: 2.0
Name: YoClient
Version: 0.0.2
Summary: Yo Client
Home-page: https://github.com/jaebradley/yo_client
Author: Jae Bradley
Author-email: jae.b.bradley@gmail.com
License: UNKNOWN
Download-URL: https://github.com/jaebradley/yo_client/tarball/0.1
Keywords: yo
Platform: UNKNOWN
Requires-Dist: requests
